quac/__init__.py
quac/_modidx.py
quac/base.py
quac/chic.py
quac/cons.py
quac/duck.py
quac/eggs.py
quac/enum.py
quac/errs.py
quac/grds.py
quac/meta.py
quac/misc.py
quac/mods.py
quac/prot.py
quac/solo.py
quac/spec.py
quac/type.py
quac-0.0.45.dist-info/LICENSE
quac-0.0.45.dist-info/METADATA
quac-0.0.45.dist-info/WHEEL
quac-0.0.45.dist-info/entry_points.txt
quac-0.0.45.dist-info/top_level.txt
quac-0.0.45.dist-info/RECORD
